cryptid/__init__.py
cryptid/core.py
cryptid-1.0.2.dist-info/METADATA
cryptid-1.0.2.dist-info/WHEEL
cryptid-1.0.2.dist-info/licenses/LICENSE
cryptid-1.0.2.dist-info/RECORD
