Metadata-Version: 2.4
Name: cryptid
Version: 1.0.2
Summary: Python tools for encrypt and decrypt
Project-URL: Homepage, https://github.com/syxhri/cryptid
Project-URL: Issues, https://github.com/syxhri/cryptid/issues
Project-URL: Repository, https://github.com/syxhri/cryptid.git
Author-email: Alfi Syahri <alfisyahri.official@gmail.com>
License: MIT License
License-File: LICENSE
Classifier: License :: OSI Approved :: MIT License
Classifier: Operating System :: OS Independent
Classifier: Programming Language :: Python :: 3
Requires-Python: >=3.7
Requires-Dist: cryptography
Requires-Dist: pillow
